_pytest_devpi_server/__init__.py
pytest_devpi_server-1.8.0.dist-info/LICENSE
pytest_devpi_server-1.8.0.dist-info/METADATA
pytest_devpi_server-1.8.0.dist-info/WHEEL
pytest_devpi_server-1.8.0.dist-info/entry_points.txt
pytest_devpi_server-1.8.0.dist-info/top_level.txt
pytest_devpi_server-1.8.0.dist-info/RECORD
